README.md
setup.py
sewingmachine/__init__.py
sewingmachine/equivalentwidths.py
sewingmachine.egg-info/PKG-INFO
sewingmachine.egg-info/SOURCES.txt
sewingmachine.egg-info/dependency_links.txt
sewingmachine.egg-info/not-zip-safe
sewingmachine.egg-info/top_level.txt