Metadata-Version: 1.0
Name: sewingmachine
Version: 0.1
Summary: the Spectral Equivalent Widths(ing) machine
Home-page: http://github.com/jmackereth/sewingmachine
Author: J. Ted Mackereth
Author-email: J.E.Mackereth@2011.ljmu.ac.uk
License: MIT
Platform: UNKNOWN
